cubicweb_compound/__init__.py
cubicweb_compound/__pkginfo__.py
cubicweb_compound/entities.py
cubicweb_compound/hooks.py
cubicweb_compound/utils.py
cubicweb_compound/views.py
cubicweb_compound/i18n/en.po
cubicweb_compound/i18n/fr.po
cubicweb_compound/migration/postcreate.py
cubicweb_compound-1.0.0.dist-info/METADATA
cubicweb_compound-1.0.0.dist-info/WHEEL
cubicweb_compound-1.0.0.dist-info/entry_points.txt
cubicweb_compound-1.0.0.dist-info/top_level.txt
cubicweb_compound-1.0.0.dist-info/RECORD
